[
  {
    "data_referencia": "01/09/2026",
    "ano": 2026,
    "mês": 9,
    "indicador": "Armazenamento",
    "unidade": "%",
    "valor": 61.9,
    "subsistema": "Sudeste/Centro-Oeste",
    "reservtorio_equivalente": "",
    "tipo_valor": "Previsto",
    "fonte": "Ampere",
    "rodada": 20260616,
    "cenario": "BASE",
    "data_publicacao": "16/06/2026"
  },
  {
    "data_referencia": "01/09/2026",
    "ano": 2026,
    "mês": 9,
    "indicador": "Armazenamento",
    "unidade": "%",
    "valor": 89.6,
    "subsistema": "Sul",
    "reservtorio_equivalente": "",
    "tipo_valor": "Previsto",
    "fonte": "Ampere",
    "rodada": 20260616,
    "cenario": "BASE",
    "data_publicacao": "16/06/2026"
  },
  {
    "data_referencia": "01/09/2026",
    "ano": 2026,
    "mês": 9,
    "indicador": "Armazenamento",
    "unidade": "%",
    "valor": 75.6,
    "subsistema": "Nordeste",
    "reservtorio_equivalente": "",
    "tipo_valor": "Previsto",
    "fonte": "Ampere",
    "rodada": 20260616,
    "cenario": "BASE",
    "data_publicacao": "16/06/2026"
  },
  {
    "data_referencia": "01/09/2026",
    "ano": 2026,
    "mês": 9,
    "indicador": "Armazenamento",
    "unidade": "%",
    "valor": 84.1,
    "subsistema": "Norte",
    "reservtorio_equivalente": "",
    "tipo_valor": "Previsto",
    "fonte": "Ampere",
    "rodada": 20260616,
    "cenario": "BASE",
    "data_publicacao": "16/06/2026"
  },
  {
    "data_referencia": "01/09/2026",
    "ano": 2026,
    "mês": 9,
    "indicador": "Armazenamento",
    "unidade": "%",
    "valor": 67.4,
    "subsistema": "SIN",
    "reservtorio_equivalente": "",
    "tipo_valor": "Previsto",
    "fonte": "Ampere",
    "rodada": 20260616,
    "cenario": "BASE",
    "data_publicacao": "16/06/2026"
  },
  {
    "data_referencia": "01/09/2026",
    "ano": 2026,
    "mês": 9,
    "indicador": "ENA",
    "unidade": "MWmed",
    "valor": 18328.0,
    "subsistema": "Sudeste/Centro-Oeste",
    "reservtorio_equivalente": "",
    "tipo_valor": "Previsto",
    "fonte": "Ampere",
    "rodada": 20260616,
    "cenario": "BASE",
    "data_publicacao": "16/06/2026"
  },
  {
    "data_referencia": "01/09/2026",
    "ano": 2026,
    "mês": 9,
    "indicador": "ENA",
    "unidade": "%",
    "valor": 94.0,
    "subsistema": "Sudeste/Centro-Oeste",
    "reservtorio_equivalente": "",
    "tipo_valor": "Previsto",
    "fonte": "Ampere",
    "rodada": 20260616,
    "cenario": "BASE",
    "data_publicacao": "16/06/2026"
  },
  {
    "data_referencia": "01/09/2026",
    "ano": 2026,
    "mês": 9,
    "indicador": "ENA",
    "unidade": "MWmed",
    "valor": 15357.0,
    "subsistema": "Sul",
    "reservtorio_equivalente": "",
    "tipo_valor": "Previsto",
    "fonte": "Ampere",
    "rodada": 20260616,
    "cenario": "BASE",
    "data_publicacao": "16/06/2026"
  },
  {
    "data_referencia": "01/09/2026",
    "ano": 2026,
    "mês": 9,
    "indicador": "ENA",
    "unidade": "%",
    "valor": 132.0,
    "subsistema": "Sul",
    "reservtorio_equivalente": "",
    "tipo_valor": "Previsto",
    "fonte": "Ampere",
    "rodada": 20260616,
    "cenario": "BASE",
    "data_publicacao": "16/06/2026"
  },
  {
    "data_referencia": "01/09/2026",
    "ano": 2026,
    "mês": 9,
    "indicador": "ENA",
    "unidade": "MWmed",
    "valor": 1861.0,
    "subsistema": "Nordeste",
    "reservtorio_equivalente": "",
    "tipo_valor": "Previsto",
    "fonte": "Ampere",
    "rodada": 20260616,
    "cenario": "BASE",
    "data_publicacao": "16/06/2026"
  },
  {
    "data_referencia": "01/09/2026",
    "ano": 2026,
    "mês": 9,
    "indicador": "ENA",
    "unidade": "%",
    "valor": 64.0,
    "subsistema": "Nordeste",
    "reservtorio_equivalente": "",
    "tipo_valor": "Previsto",
    "fonte": "Ampere",
    "rodada": 20260616,
    "cenario": "BASE",
    "data_publicacao": "16/06/2026"
  },
  {
    "data_referencia": "01/09/2026",
    "ano": 2026,
    "mês": 9,
    "indicador": "ENA",
    "unidade": "MWmed",
    "valor": 1458.0,
    "subsistema": "Norte",
    "reservtorio_equivalente": "",
    "tipo_valor": "Previsto",
    "fonte": "Ampere",
    "rodada": 20260616,
    "cenario": "BASE",
    "data_publicacao": "16/06/2026"
  },
  {
    "data_referencia": "01/09/2026",
    "ano": 2026,
    "mês": 9,
    "indicador": "ENA",
    "unidade": "%",
    "valor": 65.0,
    "subsistema": "Norte",
    "reservtorio_equivalente": "",
    "tipo_valor": "Previsto",
    "fonte": "Ampere",
    "rodada": 20260616,
    "cenario": "BASE",
    "data_publicacao": "16/06/2026"
  },
  {
    "data_referencia": "01/09/2026",
    "ano": 2026,
    "mês": 9,
    "indicador": "PLD",
    "unidade": "R$/MWh",
    "valor": 110.49,
    "subsistema": "Sudeste/Centro-Oeste",
    "reservtorio_equivalente": "",
    "tipo_valor": "Previsto",
    "fonte": "Ampere",
    "rodada": 20260616,
    "cenario": "BASE",
    "data_publicacao": "16/06/2026"
  },
  {
    "data_referencia": "01/09/2026",
    "ano": 2026,
    "mês": 9,
    "indicador": "PLD",
    "unidade": "R$/MWh",
    "valor": 110.49,
    "subsistema": "Sul",
    "reservtorio_equivalente": "",
    "tipo_valor": "Previsto",
    "fonte": "Ampere",
    "rodada": 20260616,
    "cenario": "BASE",
    "data_publicacao": "16/06/2026"
  },
  {
    "data_referencia": "01/09/2026",
    "ano": 2026,
    "mês": 9,
    "indicador": "PLD",
    "unidade": "R$/MWh",
    "valor": 110.49,
    "subsistema": "Nordeste",
    "reservtorio_equivalente": "",
    "tipo_valor": "Previsto",
    "fonte": "Ampere",
    "rodada": 20260616,
    "cenario": "BASE",
    "data_publicacao": "16/06/2026"
  },
  {
    "data_referencia": "01/09/2026",
    "ano": 2026,
    "mês": 9,
    "indicador": "PLD",
    "unidade": "R$/MWh",
    "valor": 110.49,
    "subsistema": "Norte",
    "reservtorio_equivalente": "",
    "tipo_valor": "Previsto",
    "fonte": "Ampere",
    "rodada": 20260616,
    "cenario": "BASE",
    "data_publicacao": "16/06/2026"
  },
  {
    "data_referencia": "01/08/2026",
    "ano": 2026,
    "mês": 8,
    "indicador": "Armazenamento",
    "unidade": "%",
    "valor": 64.5,
    "subsistema": "Sudeste/Centro-Oeste",
    "reservtorio_equivalente": "",
    "tipo_valor": "Previsto",
    "fonte": "Ampere",
    "rodada": 20260616,
    "cenario": "BASE",
    "data_publicacao": "16/06/2026"
  },
  {
    "data_referencia": "01/08/2026",
    "ano": 2026,
    "mês": 8,
    "indicador": "Armazenamento",
    "unidade": "%",
    "valor": 86.2,
    "subsistema": "Sul",
    "reservtorio_equivalente": "",
    "tipo_valor": "Previsto",
    "fonte": "Ampere",
    "rodada": 20260616,
    "cenario": "BASE",
    "data_publicacao": "16/06/2026"
  },
  {
    "data_referencia": "01/08/2026",
    "ano": 2026,
    "mês": 8,
    "indicador": "Armazenamento",
    "unidade": "%",
    "valor": 81.7,
    "subsistema": "Nordeste",
    "reservtorio_equivalente": "",
    "tipo_valor": "Previsto",
    "fonte": "Ampere",
    "rodada": 20260616,
    "cenario": "BASE",
    "data_publicacao": "16/06/2026"
  },
  {
    "data_referencia": "01/08/2026",
    "ano": 2026,
    "mês": 8,
    "indicador": "Armazenamento",
    "unidade": "%",
    "valor": 94.4,
    "subsistema": "Norte",
    "reservtorio_equivalente": "",
    "tipo_valor": "Previsto",
    "fonte": "Ampere",
    "rodada": 20260616,
    "cenario": "BASE",
    "data_publicacao": "16/06/2026"
  },
  {
    "data_referencia": "01/08/2026",
    "ano": 2026,
    "mês": 8,
    "indicador": "Armazenamento",
    "unidade": "%",
    "valor": 70.7,
    "subsistema": "SIN",
    "reservtorio_equivalente": "",
    "tipo_valor": "Previsto",
    "fonte": "Ampere",
    "rodada": 20260616,
    "cenario": "BASE",
    "data_publicacao": "16/06/2026"
  },
  {
    "data_referencia": "01/08/2026",
    "ano": 2026,
    "mês": 8,
    "indicador": "ENA",
    "unidade": "MWmed",
    "valor": 19266.0,
    "subsistema": "Sudeste/Centro-Oeste",
    "reservtorio_equivalente": "",
    "tipo_valor": "Previsto",
    "fonte": "Ampere",
    "rodada": 20260616,
    "cenario": "BASE",
    "data_publicacao": "16/06/2026"
  },
  {
    "data_referencia": "01/08/2026",
    "ano": 2026,
    "mês": 8,
    "indicador": "ENA",
    "unidade": "%",
    "valor": 94.0,
    "subsistema": "Sudeste/Centro-Oeste",
    "reservtorio_equivalente": "",
    "tipo_valor": "Previsto",
    "fonte": "Ampere",
    "rodada": 20260616,
    "cenario": "BASE",
    "data_publicacao": "16/06/2026"
  },
  {
    "data_referencia": "01/08/2026",
    "ano": 2026,
    "mês": 8,
    "indicador": "ENA",
    "unidade": "MWmed",
    "valor": 13227.0,
    "subsistema": "Sul",
    "reservtorio_equivalente": "",
    "tipo_valor": "Previsto",
    "fonte": "Ampere",
    "rodada": 20260616,
    "cenario": "BASE",
    "data_publicacao": "16/06/2026"
  },
  {
    "data_referencia": "01/08/2026",
    "ano": 2026,
    "mês": 8,
    "indicador": "ENA",
    "unidade": "%",
    "valor": 133.0,
    "subsistema": "Sul",
    "reservtorio_equivalente": "",
    "tipo_valor": "Previsto",
    "fonte": "Ampere",
    "rodada": 20260616,
    "cenario": "BASE",
    "data_publicacao": "16/06/2026"
  },
  {
    "data_referencia": "01/08/2026",
    "ano": 2026,
    "mês": 8,
    "indicador": "ENA",
    "unidade": "MWmed",
    "valor": 2027.0,
    "subsistema": "Nordeste",
    "reservtorio_equivalente": "",
    "tipo_valor": "Previsto",
    "fonte": "Ampere",
    "rodada": 20260616,
    "cenario": "BASE",
    "data_publicacao": "16/06/2026"
  },
  {
    "data_referencia": "01/08/2026",
    "ano": 2026,
    "mês": 8,
    "indicador": "ENA",
    "unidade": "%",
    "valor": 62.0,
    "subsistema": "Nordeste",
    "reservtorio_equivalente": "",
    "tipo_valor": "Previsto",
    "fonte": "Ampere",
    "rodada": 20260616,
    "cenario": "BASE",
    "data_publicacao": "16/06/2026"
  },
  {
    "data_referencia": "01/08/2026",
    "ano": 2026,
    "mês": 8,
    "indicador": "ENA",
    "unidade": "MWmed",
    "valor": 2273.0,
    "subsistema": "Norte",
    "reservtorio_equivalente": "",
    "tipo_valor": "Previsto",
    "fonte": "Ampere",
    "rodada": 20260616,
    "cenario": "BASE",
    "data_publicacao": "16/06/2026"
  },
  {
    "data_referencia": "01/08/2026",
    "ano": 2026,
    "mês": 8,
    "indicador": "ENA",
    "unidade": "%",
    "valor": 72.0,
    "subsistema": "Norte",
    "reservtorio_equivalente": "",
    "tipo_valor": "Previsto",
    "fonte": "Ampere",
    "rodada": 20260616,
    "cenario": "BASE",
    "data_publicacao": "16/06/2026"
  },
  {
    "data_referencia": "01/08/2026",
    "ano": 2026,
    "mês": 8,
    "indicador": "PLD",
    "unidade": "R$/MWh",
    "valor": 81.45,
    "subsistema": "Sudeste/Centro-Oeste",
    "reservtorio_equivalente": "",
    "tipo_valor": "Previsto",
    "fonte": "Ampere",
    "rodada": 20260616,
    "cenario": "BASE",
    "data_publicacao": "16/06/2026"
  },
  {
    "data_referencia": "01/08/2026",
    "ano": 2026,
    "mês": 8,
    "indicador": "PLD",
    "unidade": "R$/MWh",
    "valor": 81.45,
    "subsistema": "Sul",
    "reservtorio_equivalente": "",
    "tipo_valor": "Previsto",
    "fonte": "Ampere",
    "rodada": 20260616,
    "cenario": "BASE",
    "data_publicacao": "16/06/2026"
  },
  {
    "data_referencia": "01/08/2026",
    "ano": 2026,
    "mês": 8,
    "indicador": "PLD",
    "unidade": "R$/MWh",
    "valor": 81.45,
    "subsistema": "Nordeste",
    "reservtorio_equivalente": "",
    "tipo_valor": "Previsto",
    "fonte": "Ampere",
    "rodada": 20260616,
    "cenario": "BASE",
    "data_publicacao": "16/06/2026"
  },
  {
    "data_referencia": "01/08/2026",
    "ano": 2026,
    "mês": 8,
    "indicador": "PLD",
    "unidade": "R$/MWh",
    "valor": 81.45,
    "subsistema": "Norte",
    "reservtorio_equivalente": "",
    "tipo_valor": "Previsto",
    "fonte": "Ampere",
    "rodada": 20260616,
    "cenario": "BASE",
    "data_publicacao": "16/06/2026"
  },
  {
    "data_referencia": "01/07/2026",
    "ano": 2026,
    "mês": 7,
    "indicador": "Armazenamento",
    "unidade": "%",
    "valor": 66.2,
    "subsistema": "Sudeste/Centro-Oeste",
    "reservtorio_equivalente": "",
    "tipo_valor": "Previsto",
    "fonte": "Ampere",
    "rodada": 20260616,
    "cenario": "BASE",
    "data_publicacao": "16/06/2026"
  },
  {
    "data_referencia": "01/07/2026",
    "ano": 2026,
    "mês": 7,
    "indicador": "Armazenamento",
    "unidade": "%",
    "valor": 89.8,
    "subsistema": "Sul",
    "reservtorio_equivalente": "",
    "tipo_valor": "Previsto",
    "fonte": "Ampere",
    "rodada": 20260616,
    "cenario": "BASE",
    "data_publicacao": "16/06/2026"
  },
  {
    "data_referencia": "01/07/2026",
    "ano": 2026,
    "mês": 7,
    "indicador": "Armazenamento",
    "unidade": "%",
    "valor": 85.9,
    "subsistema": "Nordeste",
    "reservtorio_equivalente": "",
    "tipo_valor": "Previsto",
    "fonte": "Ampere",
    "rodada": 20260616,
    "cenario": "BASE",
    "data_publicacao": "16/06/2026"
  },
  {
    "data_referencia": "01/07/2026",
    "ano": 2026,
    "mês": 7,
    "indicador": "Armazenamento",
    "unidade": "%",
    "valor": 96.3,
    "subsistema": "Norte",
    "reservtorio_equivalente": "",
    "tipo_valor": "Previsto",
    "fonte": "Ampere",
    "rodada": 20260616,
    "cenario": "BASE",
    "data_publicacao": "16/06/2026"
  },
  {
    "data_referencia": "01/07/2026",
    "ano": 2026,
    "mês": 7,
    "indicador": "Armazenamento",
    "unidade": "%",
    "valor": 72.9,
    "subsistema": "SIN",
    "reservtorio_equivalente": "",
    "tipo_valor": "Previsto",
    "fonte": "Ampere",
    "rodada": 20260616,
    "cenario": "BASE",
    "data_publicacao": "16/06/2026"
  },
  {
    "data_referencia": "01/07/2026",
    "ano": 2026,
    "mês": 7,
    "indicador": "ENA",
    "unidade": "MWmed",
    "valor": 23469.0,
    "subsistema": "Sudeste/Centro-Oeste",
    "reservtorio_equivalente": "",
    "tipo_valor": "Previsto",
    "fonte": "Ampere",
    "rodada": 20260616,
    "cenario": "BASE",
    "data_publicacao": "16/06/2026"
  },
  {
    "data_referencia": "01/07/2026",
    "ano": 2026,
    "mês": 7,
    "indicador": "ENA",
    "unidade": "%",
    "valor": 92.0,
    "subsistema": "Sudeste/Centro-Oeste",
    "reservtorio_equivalente": "",
    "tipo_valor": "Previsto",
    "fonte": "Ampere",
    "rodada": 20260616,
    "cenario": "BASE",
    "data_publicacao": "16/06/2026"
  },
  {
    "data_referencia": "01/07/2026",
    "ano": 2026,
    "mês": 7,
    "indicador": "ENA",
    "unidade": "MWmed",
    "valor": 15006.0,
    "subsistema": "Sul",
    "reservtorio_equivalente": "",
    "tipo_valor": "Previsto",
    "fonte": "Ampere",
    "rodada": 20260616,
    "cenario": "BASE",
    "data_publicacao": "16/06/2026"
  },
  {
    "data_referencia": "01/07/2026",
    "ano": 2026,
    "mês": 7,
    "indicador": "ENA",
    "unidade": "%",
    "valor": 136.0,
    "subsistema": "Sul",
    "reservtorio_equivalente": "",
    "tipo_valor": "Previsto",
    "fonte": "Ampere",
    "rodada": 20260616,
    "cenario": "BASE",
    "data_publicacao": "16/06/2026"
  },
  {
    "data_referencia": "01/07/2026",
    "ano": 2026,
    "mês": 7,
    "indicador": "ENA",
    "unidade": "MWmed",
    "valor": 2246.0,
    "subsistema": "Nordeste",
    "reservtorio_equivalente": "",
    "tipo_valor": "Previsto",
    "fonte": "Ampere",
    "rodada": 20260616,
    "cenario": "BASE",
    "data_publicacao": "16/06/2026"
  },
  {
    "data_referencia": "01/07/2026",
    "ano": 2026,
    "mês": 7,
    "indicador": "ENA",
    "unidade": "%",
    "valor": 60.0,
    "subsistema": "Nordeste",
    "reservtorio_equivalente": "",
    "tipo_valor": "Previsto",
    "fonte": "Ampere",
    "rodada": 20260616,
    "cenario": "BASE",
    "data_publicacao": "16/06/2026"
  },
  {
    "data_referencia": "01/07/2026",
    "ano": 2026,
    "mês": 7,
    "indicador": "ENA",
    "unidade": "MWmed",
    "valor": 3723.0,
    "subsistema": "Norte",
    "reservtorio_equivalente": "",
    "tipo_valor": "Previsto",
    "fonte": "Ampere",
    "rodada": 20260616,
    "cenario": "BASE",
    "data_publicacao": "16/06/2026"
  },
  {
    "data_referencia": "01/07/2026",
    "ano": 2026,
    "mês": 7,
    "indicador": "ENA",
    "unidade": "%",
    "valor": 71.0,
    "subsistema": "Norte",
    "reservtorio_equivalente": "",
    "tipo_valor": "Previsto",
    "fonte": "Ampere",
    "rodada": 20260616,
    "cenario": "BASE",
    "data_publicacao": "16/06/2026"
  },
  {
    "data_referencia": "01/07/2026",
    "ano": 2026,
    "mês": 7,
    "indicador": "PLD",
    "unidade": "R$/MWh",
    "valor": 57.31,
    "subsistema": "Sudeste/Centro-Oeste",
    "reservtorio_equivalente": "",
    "tipo_valor": "Previsto",
    "fonte": "Ampere",
    "rodada": 20260616,
    "cenario": "BASE",
    "data_publicacao": "16/06/2026"
  },
  {
    "data_referencia": "01/07/2026",
    "ano": 2026,
    "mês": 7,
    "indicador": "PLD",
    "unidade": "R$/MWh",
    "valor": 57.31,
    "subsistema": "Sul",
    "reservtorio_equivalente": "",
    "tipo_valor": "Previsto",
    "fonte": "Ampere",
    "rodada": 20260616,
    "cenario": "BASE",
    "data_publicacao": "16/06/2026"
  },
  {
    "data_referencia": "01/07/2026",
    "ano": 2026,
    "mês": 7,
    "indicador": "PLD",
    "unidade": "R$/MWh",
    "valor": 57.31,
    "subsistema": "Nordeste",
    "reservtorio_equivalente": "",
    "tipo_valor": "Previsto",
    "fonte": "Ampere",
    "rodada": 20260616,
    "cenario": "BASE",
    "data_publicacao": "16/06/2026"
  },
  {
    "data_referencia": "01/07/2026",
    "ano": 2026,
    "mês": 7,
    "indicador": "PLD",
    "unidade": "R$/MWh",
    "valor": 57.31,
    "subsistema": "Norte",
    "reservtorio_equivalente": "",
    "tipo_valor": "Previsto",
    "fonte": "Ampere",
    "rodada": 20260616,
    "cenario": "BASE",
    "data_publicacao": "16/06/2026"
  },
  {
    "data_referencia": "01/06/2026",
    "ano": 2026,
    "mês": 6,
    "indicador": "Armazenamento",
    "unidade": "%",
    "valor": 66.5,
    "subsistema": "Sudeste/Centro-Oeste",
    "reservtorio_equivalente": "",
    "tipo_valor": "Previsto",
    "fonte": "Ampere",
    "rodada": 20260616,
    "cenario": "BASE",
    "data_publicacao": "16/06/2026"
  },
  {
    "data_referencia": "01/06/2026",
    "ano": 2026,
    "mês": 6,
    "indicador": "Armazenamento",
    "unidade": "%",
    "valor": 58.3,
    "subsistema": "Sul",
    "reservtorio_equivalente": "",
    "tipo_valor": "Previsto",
    "fonte": "Ampere",
    "rodada": 20260616,
    "cenario": "BASE",
    "data_publicacao": "16/06/2026"
  },
  {
    "data_referencia": "01/06/2026",
    "ano": 2026,
    "mês": 6,
    "indicador": "Armazenamento",
    "unidade": "%",
    "valor": 90.3,
    "subsistema": "Nordeste",
    "reservtorio_equivalente": "",
    "tipo_valor": "Previsto",
    "fonte": "Ampere",
    "rodada": 20260616,
    "cenario": "BASE",
    "data_publicacao": "16/06/2026"
  },
  {
    "data_referencia": "01/06/2026",
    "ano": 2026,
    "mês": 6,
    "indicador": "Armazenamento",
    "unidade": "%",
    "valor": 97.6,
    "subsistema": "Norte",
    "reservtorio_equivalente": "",
    "tipo_valor": "Previsto",
    "fonte": "Ampere",
    "rodada": 20260616,
    "cenario": "BASE",
    "data_publicacao": "16/06/2026"
  },
  {
    "data_referencia": "01/06/2026",
    "ano": 2026,
    "mês": 6,
    "indicador": "Armazenamento",
    "unidade": "%",
    "valor": 71.8,
    "subsistema": "SIN",
    "reservtorio_equivalente": "",
    "tipo_valor": "Previsto",
    "fonte": "Ampere",
    "rodada": 20260616,
    "cenario": "BASE",
    "data_publicacao": "16/06/2026"
  },
  {
    "data_referencia": "01/06/2026",
    "ano": 2026,
    "mês": 6,
    "indicador": "ENA",
    "unidade": "MWmed",
    "valor": 28696.0,
    "subsistema": "Sudeste/Centro-Oeste",
    "reservtorio_equivalente": "",
    "tipo_valor": "Previsto",
    "fonte": "Ampere",
    "rodada": 20260616,
    "cenario": "BASE",
    "data_publicacao": "16/06/2026"
  },
  {
    "data_referencia": "01/06/2026",
    "ano": 2026,
    "mês": 6,
    "indicador": "ENA",
    "unidade": "%",
    "valor": 88.0,
    "subsistema": "Sudeste/Centro-Oeste",
    "reservtorio_equivalente": "",
    "tipo_valor": "Previsto",
    "fonte": "Ampere",
    "rodada": 20260616,
    "cenario": "BASE",
    "data_publicacao": "16/06/2026"
  },
  {
    "data_referencia": "01/06/2026",
    "ano": 2026,
    "mês": 6,
    "indicador": "ENA",
    "unidade": "MWmed",
    "valor": 7898.0,
    "subsistema": "Sul",
    "reservtorio_equivalente": "",
    "tipo_valor": "Previsto",
    "fonte": "Ampere",
    "rodada": 20260616,
    "cenario": "BASE",
    "data_publicacao": "16/06/2026"
  },
  {
    "data_referencia": "01/06/2026",
    "ano": 2026,
    "mês": 6,
    "indicador": "ENA",
    "unidade": "%",
    "valor": 74.0,
    "subsistema": "Sul",
    "reservtorio_equivalente": "",
    "tipo_valor": "Previsto",
    "fonte": "Ampere",
    "rodada": 20260616,
    "cenario": "BASE",
    "data_publicacao": "16/06/2026"
  },
  {
    "data_referencia": "01/06/2026",
    "ano": 2026,
    "mês": 6,
    "indicador": "ENA",
    "unidade": "MWmed",
    "valor": 2575.0,
    "subsistema": "Nordeste",
    "reservtorio_equivalente": "",
    "tipo_valor": "Previsto",
    "fonte": "Ampere",
    "rodada": 20260616,
    "cenario": "BASE",
    "data_publicacao": "16/06/2026"
  },
  {
    "data_referencia": "01/06/2026",
    "ano": 2026,
    "mês": 6,
    "indicador": "ENA",
    "unidade": "%",
    "valor": 57.0,
    "subsistema": "Nordeste",
    "reservtorio_equivalente": "",
    "tipo_valor": "Previsto",
    "fonte": "Ampere",
    "rodada": 20260616,
    "cenario": "BASE",
    "data_publicacao": "16/06/2026"
  },
  {
    "data_referencia": "01/06/2026",
    "ano": 2026,
    "mês": 6,
    "indicador": "ENA",
    "unidade": "MWmed",
    "valor": 6663.0,
    "subsistema": "Norte",
    "reservtorio_equivalente": "",
    "tipo_valor": "Previsto",
    "fonte": "Ampere",
    "rodada": 20260616,
    "cenario": "BASE",
    "data_publicacao": "16/06/2026"
  },
  {
    "data_referencia": "01/06/2026",
    "ano": 2026,
    "mês": 6,
    "indicador": "ENA",
    "unidade": "%",
    "valor": 63.0,
    "subsistema": "Norte",
    "reservtorio_equivalente": "",
    "tipo_valor": "Previsto",
    "fonte": "Ampere",
    "rodada": 20260616,
    "cenario": "BASE",
    "data_publicacao": "16/06/2026"
  },
  {
    "data_referencia": "01/06/2026",
    "ano": 2026,
    "mês": 6,
    "indicador": "PLD",
    "unidade": "R$/MWh",
    "valor": 193.94,
    "subsistema": "Sudeste/Centro-Oeste",
    "reservtorio_equivalente": "",
    "tipo_valor": "Previsto",
    "fonte": "Ampere",
    "rodada": 20260616,
    "cenario": "BASE",
    "data_publicacao": "16/06/2026"
  },
  {
    "data_referencia": "01/06/2026",
    "ano": 2026,
    "mês": 6,
    "indicador": "PLD",
    "unidade": "R$/MWh",
    "valor": 193.94,
    "subsistema": "Sul",
    "reservtorio_equivalente": "",
    "tipo_valor": "Previsto",
    "fonte": "Ampere",
    "rodada": 20260616,
    "cenario": "BASE",
    "data_publicacao": "16/06/2026"
  },
  {
    "data_referencia": "01/06/2026",
    "ano": 2026,
    "mês": 6,
    "indicador": "PLD",
    "unidade": "R$/MWh",
    "valor": 193.94,
    "subsistema": "Nordeste",
    "reservtorio_equivalente": "",
    "tipo_valor": "Previsto",
    "fonte": "Ampere",
    "rodada": 20260616,
    "cenario": "BASE",
    "data_publicacao": "16/06/2026"
  },
  {
    "data_referencia": "01/06/2026",
    "ano": 2026,
    "mês": 6,
    "indicador": "PLD",
    "unidade": "R$/MWh",
    "valor": 193.94,
    "subsistema": "Norte",
    "reservtorio_equivalente": "",
    "tipo_valor": "Previsto",
    "fonte": "Ampere",
    "rodada": 20260616,
    "cenario": "BASE",
    "data_publicacao": "16/06/2026"
  },
  {
    "data_referencia": "01/09/2026",
    "ano": 2026,
    "mês": 9,
    "indicador": "Armazenamento",
    "unidade": "%",
    "valor": 59.8,
    "subsistema": "Sudeste/Centro-Oeste",
    "reservtorio_equivalente": "",
    "tipo_valor": "Previsto",
    "fonte": "Ampere",
    "rodada": 20260609,
    "cenario": "BASE",
    "data_publicacao": "09/06/2026"
  },
  {
    "data_referencia": "01/09/2026",
    "ano": 2026,
    "mês": 9,
    "indicador": "Armazenamento",
    "unidade": "%",
    "valor": 76.7,
    "subsistema": "Sul",
    "reservtorio_equivalente": "",
    "tipo_valor": "Previsto",
    "fonte": "Ampere",
    "rodada": 20260609,
    "cenario": "BASE",
    "data_publicacao": "09/06/2026"
  },
  {
    "data_referencia": "01/09/2026",
    "ano": 2026,
    "mês": 9,
    "indicador": "Armazenamento",
    "unidade": "%",
    "valor": 77.3,
    "subsistema": "Nordeste",
    "reservtorio_equivalente": "",
    "tipo_valor": "Previsto",
    "fonte": "Ampere",
    "rodada": 20260609,
    "cenario": "BASE",
    "data_publicacao": "09/06/2026"
  },
  {
    "data_referencia": "01/09/2026",
    "ano": 2026,
    "mês": 9,
    "indicador": "Armazenamento",
    "unidade": "%",
    "valor": 84.0,
    "subsistema": "Norte",
    "reservtorio_equivalente": "",
    "tipo_valor": "Previsto",
    "fonte": "Ampere",
    "rodada": 20260609,
    "cenario": "BASE",
    "data_publicacao": "09/06/2026"
  },
  {
    "data_referencia": "01/09/2026",
    "ano": 2026,
    "mês": 9,
    "indicador": "Armazenamento",
    "unidade": "%",
    "valor": 65.4,
    "subsistema": "SIN",
    "reservtorio_equivalente": "",
    "tipo_valor": "Previsto",
    "fonte": "Ampere",
    "rodada": 20260609,
    "cenario": "BASE",
    "data_publicacao": "09/06/2026"
  },
  {
    "data_referencia": "01/09/2026",
    "ano": 2026,
    "mês": 9,
    "indicador": "ENA",
    "unidade": "MWmed",
    "valor": 17212.0,
    "subsistema": "Sudeste/Centro-Oeste",
    "reservtorio_equivalente": "",
    "tipo_valor": "Previsto",
    "fonte": "Ampere",
    "rodada": 20260609,
    "cenario": "BASE",
    "data_publicacao": "09/06/2026"
  },
  {
    "data_referencia": "01/09/2026",
    "ano": 2026,
    "mês": 9,
    "indicador": "ENA",
    "unidade": "%",
    "valor": 88.0,
    "subsistema": "Sudeste/Centro-Oeste",
    "reservtorio_equivalente": "",
    "tipo_valor": "Previsto",
    "fonte": "Ampere",
    "rodada": 20260609,
    "cenario": "BASE",
    "data_publicacao": "09/06/2026"
  },
  {
    "data_referencia": "01/09/2026",
    "ano": 2026,
    "mês": 9,
    "indicador": "ENA",
    "unidade": "MWmed",
    "valor": 13491.0,
    "subsistema": "Sul",
    "reservtorio_equivalente": "",
    "tipo_valor": "Previsto",
    "fonte": "Ampere",
    "rodada": 20260609,
    "cenario": "BASE",
    "data_publicacao": "09/06/2026"
  },
  {
    "data_referencia": "01/09/2026",
    "ano": 2026,
    "mês": 9,
    "indicador": "ENA",
    "unidade": "%",
    "valor": 116.0,
    "subsistema": "Sul",
    "reservtorio_equivalente": "",
    "tipo_valor": "Previsto",
    "fonte": "Ampere",
    "rodada": 20260609,
    "cenario": "BASE",
    "data_publicacao": "09/06/2026"
  },
  {
    "data_referencia": "01/09/2026",
    "ano": 2026,
    "mês": 9,
    "indicador": "ENA",
    "unidade": "MWmed",
    "valor": 2011.0,
    "subsistema": "Nordeste",
    "reservtorio_equivalente": "",
    "tipo_valor": "Previsto",
    "fonte": "Ampere",
    "rodada": 20260609,
    "cenario": "BASE",
    "data_publicacao": "09/06/2026"
  },
  {
    "data_referencia": "01/09/2026",
    "ano": 2026,
    "mês": 9,
    "indicador": "ENA",
    "unidade": "%",
    "valor": 69.0,
    "subsistema": "Nordeste",
    "reservtorio_equivalente": "",
    "tipo_valor": "Previsto",
    "fonte": "Ampere",
    "rodada": 20260609,
    "cenario": "BASE",
    "data_publicacao": "09/06/2026"
  },
  {
    "data_referencia": "01/09/2026",
    "ano": 2026,
    "mês": 9,
    "indicador": "ENA",
    "unidade": "MWmed",
    "valor": 1469.0,
    "subsistema": "Norte",
    "reservtorio_equivalente": "",
    "tipo_valor": "Previsto",
    "fonte": "Ampere",
    "rodada": 20260609,
    "cenario": "BASE",
    "data_publicacao": "09/06/2026"
  },
  {
    "data_referencia": "01/09/2026",
    "ano": 2026,
    "mês": 9,
    "indicador": "ENA",
    "unidade": "%",
    "valor": 65.0,
    "subsistema": "Norte",
    "reservtorio_equivalente": "",
    "tipo_valor": "Previsto",
    "fonte": "Ampere",
    "rodada": 20260609,
    "cenario": "BASE",
    "data_publicacao": "09/06/2026"
  },
  {
    "data_referencia": "01/09/2026",
    "ano": 2026,
    "mês": 9,
    "indicador": "PLD",
    "unidade": "R$/MWh",
    "valor": 77.07,
    "subsistema": "Sudeste/Centro-Oeste",
    "reservtorio_equivalente": "",
    "tipo_valor": "Previsto",
    "fonte": "Ampere",
    "rodada": 20260609,
    "cenario": "BASE",
    "data_publicacao": "09/06/2026"
  },
  {
    "data_referencia": "01/09/2026",
    "ano": 2026,
    "mês": 9,
    "indicador": "PLD",
    "unidade": "R$/MWh",
    "valor": 77.07,
    "subsistema": "Sul",
    "reservtorio_equivalente": "",
    "tipo_valor": "Previsto",
    "fonte": "Ampere",
    "rodada": 20260609,
    "cenario": "BASE",
    "data_publicacao": "09/06/2026"
  },
  {
    "data_referencia": "01/09/2026",
    "ano": 2026,
    "mês": 9,
    "indicador": "PLD",
    "unidade": "R$/MWh",
    "valor": 77.07,
    "subsistema": "Nordeste",
    "reservtorio_equivalente": "",
    "tipo_valor": "Previsto",
    "fonte": "Ampere",
    "rodada": 20260609,
    "cenario": "BASE",
    "data_publicacao": "09/06/2026"
  },
  {
    "data_referencia": "01/09/2026",
    "ano": 2026,
    "mês": 9,
    "indicador": "PLD",
    "unidade": "R$/MWh",
    "valor": 77.07,
    "subsistema": "Norte",
    "reservtorio_equivalente": "",
    "tipo_valor": "Previsto",
    "fonte": "Ampere",
    "rodada": 20260609,
    "cenario": "BASE",
    "data_publicacao": "09/06/2026"
  },
  {
    "data_referencia": "01/08/2026",
    "ano": 2026,
    "mês": 8,
    "indicador": "Armazenamento",
    "unidade": "%",
    "valor": 63.4,
    "subsistema": "Sudeste/Centro-Oeste",
    "reservtorio_equivalente": "",
    "tipo_valor": "Previsto",
    "fonte": "Ampere",
    "rodada": 20260609,
    "cenario": "BASE",
    "data_publicacao": "09/06/2026"
  },
  {
    "data_referencia": "01/08/2026",
    "ano": 2026,
    "mês": 8,
    "indicador": "Armazenamento",
    "unidade": "%",
    "valor": 80.5,
    "subsistema": "Sul",
    "reservtorio_equivalente": "",
    "tipo_valor": "Previsto",
    "fonte": "Ampere",
    "rodada": 20260609,
    "cenario": "BASE",
    "data_publicacao": "09/06/2026"
  },
  {
    "data_referencia": "01/08/2026",
    "ano": 2026,
    "mês": 8,
    "indicador": "Armazenamento",
    "unidade": "%",
    "valor": 81.9,
    "subsistema": "Nordeste",
    "reservtorio_equivalente": "",
    "tipo_valor": "Previsto",
    "fonte": "Ampere",
    "rodada": 20260609,
    "cenario": "BASE",
    "data_publicacao": "09/06/2026"
  },
  {
    "data_referencia": "01/08/2026",
    "ano": 2026,
    "mês": 8,
    "indicador": "Armazenamento",
    "unidade": "%",
    "valor": 94.1,
    "subsistema": "Norte",
    "reservtorio_equivalente": "",
    "tipo_valor": "Previsto",
    "fonte": "Ampere",
    "rodada": 20260609,
    "cenario": "BASE",
    "data_publicacao": "09/06/2026"
  },
  {
    "data_referencia": "01/08/2026",
    "ano": 2026,
    "mês": 8,
    "indicador": "Armazenamento",
    "unidade": "%",
    "valor": 69.5,
    "subsistema": "SIN",
    "reservtorio_equivalente": "",
    "tipo_valor": "Previsto",
    "fonte": "Ampere",
    "rodada": 20260609,
    "cenario": "BASE",
    "data_publicacao": "09/06/2026"
  },
  {
    "data_referencia": "01/08/2026",
    "ano": 2026,
    "mês": 8,
    "indicador": "ENA",
    "unidade": "MWmed",
    "valor": 20123.0,
    "subsistema": "Sudeste/Centro-Oeste",
    "reservtorio_equivalente": "",
    "tipo_valor": "Previsto",
    "fonte": "Ampere",
    "rodada": 20260609,
    "cenario": "BASE",
    "data_publicacao": "09/06/2026"
  },
  {
    "data_referencia": "01/08/2026",
    "ano": 2026,
    "mês": 8,
    "indicador": "ENA",
    "unidade": "%",
    "valor": 98.0,
    "subsistema": "Sudeste/Centro-Oeste",
    "reservtorio_equivalente": "",
    "tipo_valor": "Previsto",
    "fonte": "Ampere",
    "rodada": 20260609,
    "cenario": "BASE",
    "data_publicacao": "09/06/2026"
  },
  {
    "data_referencia": "01/08/2026",
    "ano": 2026,
    "mês": 8,
    "indicador": "ENA",
    "unidade": "MWmed",
    "valor": 10103.0,
    "subsistema": "Sul",
    "reservtorio_equivalente": "",
    "tipo_valor": "Previsto",
    "fonte": "Ampere",
    "rodada": 20260609,
    "cenario": "BASE",
    "data_publicacao": "09/06/2026"
  },
  {
    "data_referencia": "01/08/2026",
    "ano": 2026,
    "mês": 8,
    "indicador": "ENA",
    "unidade": "%",
    "valor": 102.0,
    "subsistema": "Sul",
    "reservtorio_equivalente": "",
    "tipo_valor": "Previsto",
    "fonte": "Ampere",
    "rodada": 20260609,
    "cenario": "BASE",
    "data_publicacao": "09/06/2026"
  },
  {
    "data_referencia": "01/08/2026",
    "ano": 2026,
    "mês": 8,
    "indicador": "ENA",
    "unidade": "MWmed",
    "valor": 2170.0,
    "subsistema": "Nordeste",
    "reservtorio_equivalente": "",
    "tipo_valor": "Previsto",
    "fonte": "Ampere",
    "rodada": 20260609,
    "cenario": "BASE",
    "data_publicacao": "09/06/2026"
  },
  {
    "data_referencia": "01/08/2026",
    "ano": 2026,
    "mês": 8,
    "indicador": "ENA",
    "unidade": "%",
    "valor": 67.0,
    "subsistema": "Nordeste",
    "reservtorio_equivalente": "",
    "tipo_valor": "Previsto",
    "fonte": "Ampere",
    "rodada": 20260609,
    "cenario": "BASE",
    "data_publicacao": "09/06/2026"
  },
  {
    "data_referencia": "01/08/2026",
    "ano": 2026,
    "mês": 8,
    "indicador": "ENA",
    "unidade": "MWmed",
    "valor": 2297.0,
    "subsistema": "Norte",
    "reservtorio_equivalente": "",
    "tipo_valor": "Previsto",
    "fonte": "Ampere",
    "rodada": 20260609,
    "cenario": "BASE",
    "data_publicacao": "09/06/2026"
  },
  {
    "data_referencia": "01/08/2026",
    "ano": 2026,
    "mês": 8,
    "indicador": "ENA",
    "unidade": "%",
    "valor": 73.0,
    "subsistema": "Norte",
    "reservtorio_equivalente": "",
    "tipo_valor": "Previsto",
    "fonte": "Ampere",
    "rodada": 20260609,
    "cenario": "BASE",
    "data_publicacao": "09/06/2026"
  },
  {
    "data_referencia": "01/08/2026",
    "ano": 2026,
    "mês": 8,
    "indicador": "PLD",
    "unidade": "R$/MWh",
    "valor": 74.66,
    "subsistema": "Sudeste/Centro-Oeste",
    "reservtorio_equivalente": "",
    "tipo_valor": "Previsto",
    "fonte": "Ampere",
    "rodada": 20260609,
    "cenario": "BASE",
    "data_publicacao": "09/06/2026"
  },
  {
    "data_referencia": "01/08/2026",
    "ano": 2026,
    "mês": 8,
    "indicador": "PLD",
    "unidade": "R$/MWh",
    "valor": 74.66,
    "subsistema": "Sul",
    "reservtorio_equivalente": "",
    "tipo_valor": "Previsto",
    "fonte": "Ampere",
    "rodada": 20260609,
    "cenario": "BASE",
    "data_publicacao": "09/06/2026"
  }
]